pdftextract/__init__.py
pdftextract/main.py
pdftextract/utils.py
pdftextract/xpdf/pdfimages.exe
pdftextract/xpdf/pdfinfo.exe
pdftextract/xpdf/pdftotext.exe
pdftextract-0.0.5.dist-info/LICENSE.txt
pdftextract-0.0.5.dist-info/METADATA
pdftextract-0.0.5.dist-info/WHEEL
pdftextract-0.0.5.dist-info/top_level.txt
pdftextract-0.0.5.dist-info/RECORD
