Metadata-Version: 2.1
Name: pdftextract
Version: 0.0.5
Summary: a very fast and efficient text and image pdf extractor.
Home-page: https://github.com/Bnilss/pdftextract
Author: Iliass Benali
Author-email: iliassben97@gmail.com
License: UNKNOWN
Keywords: pdf,text extractor,pdf text extractor,pdf images extractor,pdf parser,pdf text
Platform: UNKNOWN
Classifier: Programming Language :: Python :: 2
Classifier: Programming Language :: Python :: 3
Classifier: Programming Language :: Python :: 3.6
Classifier: Programming Language :: Python :: 3.7
Classifier: Programming Language :: Python :: 3.8
Classifier: License :: OSI Approved :: GNU General Public License v3 (GPLv3)
Classifier: Operating System :: Microsoft :: Windows
